indipyserver/__init__.py
indipyserver/exdriver.py
indipyserver/ipyserver.py
indipyserver/remote.py
indipyserver-0.0.2.dist-info/licenses/LICENSE
indipyserver-0.0.2.dist-info/WHEEL
indipyserver-0.0.2.dist-info/METADATA
indipyserver-0.0.2.dist-info/RECORD
