Metadata-Version: 2.4
Name: indipyserver
Version: 0.0.2
Summary: Server for the INDI protocol.
Keywords: indi,server,astronomy,instrument,remote,control
Author-email: Bernard Czenkusz <bernie@skipole.co.uk>
Requires-Python: >=3.11
Classifier: License :: OSI Approved :: MIT License
Classifier: Operating System :: POSIX :: Linux
Classifier: Topic :: Scientific/Engineering :: Astronomy
Classifier: Topic :: Scientific/Engineering :: Interface Engine/Protocol Translator
License-File: LICENSE
Project-URL: Documentation, https://indipyserver.readthedocs.io
Project-URL: Source, https://github.com/bernie-skipole/indipyserver
